cetragm/__init__.py
cetragm/audio.py
cetragm/bag.py
cetragm/config.py
cetragm/controls.py
cetragm/draw.py
cetragm/game.py
cetragm/main.py
cetragm/player.py
cetragm/srs.py
cetragm/tables.py
cetragm/ui.py
cetragm/ui.txt
cetragm/ui_controls.py
cetragm-0.1.9.dist-info/licenses/LICENSE
cetragm-0.1.9.dist-info/WHEEL
cetragm-0.1.9.dist-info/entry_points.txt
cetragm-0.1.9.dist-info/METADATA
cetragm-0.1.9.dist-info/RECORD
