Metadata-Version: 2.4
Name: cetragm
Version: 0.1.9
Summary: Cetra Grand Master | An oddly familiar block stacker in the command line!
License-Expression: GPL-3.0-only
License-File: LICENSE
Requires-Dist: pygame>=2.6.1
Requires-Python: >=3.12
